console_sudoku/__init__.py
console_sudoku/game.py
console_sudoku/game_runner.py
console_sudoku/sudoku_generator.py
console_sudoku/sudoku_runner.py
console_sudoku/sudoku_solver.py
console_sudoku-0.1.0.dist-info/METADATA
console_sudoku-0.1.0.dist-info/WHEEL
console_sudoku-0.1.0.dist-info/licenses/LICENSE
console_sudoku-0.1.0.dist-info/RECORD
