Metadata-Version: 2.3
Name: console_sudoku
Version: 0.1.0
Summary: A simple command-line version of the classic game Sudoku!
Project-URL: Homepage, https://github.com/SulKhu/Sudoku
Project-URL: Issues, https://github.com/SulKhu/Sudoku/issues
Author-email: Sulaimaan Khurrum <sul.khu@gmail.com>
License-File: LICENSE
Classifier: License :: OSI Approved :: MIT License
Classifier: Operating System :: OS Independent
Classifier: Programming Language :: Python :: 3
Requires-Python: >=3.8
